netbox_plugin_mclag/__init__.py
netbox_plugin_mclag/choices.py
netbox_plugin_mclag/filtersets.py
netbox_plugin_mclag/forms.py
netbox_plugin_mclag/models.py
netbox_plugin_mclag/navigation.py
netbox_plugin_mclag/search.py
netbox_plugin_mclag/tables.py
netbox_plugin_mclag/template_content.py
netbox_plugin_mclag/urls.py
netbox_plugin_mclag/util.py
netbox_plugin_mclag/views.py
netbox_plugin_mclag/api/__init__.py
netbox_plugin_mclag/api/serializers.py
netbox_plugin_mclag/api/urls.py
netbox_plugin_mclag/api/views.py
netbox_plugin_mclag/migrations/0001_initial.py
netbox_plugin_mclag/migrations/0002_alter_mcdomain_options_alter_mclag_options_and_more.py
netbox_plugin_mclag/migrations/0003_mclag_type.py
netbox_plugin_mclag/migrations/__init__.py
netbox_plugin_mclag/templates/netbox_plugin_mclag/button.html
netbox_plugin_mclag/templates/netbox_plugin_mclag/mcdomain.html
netbox_plugin_mclag/templates/netbox_plugin_mclag/mclag.html
netbox_plugin_mclag-0.3.1.dist-info/licenses/LICENSE
netbox_plugin_mclag-0.3.1.dist-info/METADATA
netbox_plugin_mclag-0.3.1.dist-info/WHEEL
netbox_plugin_mclag-0.3.1.dist-info/top_level.txt
netbox_plugin_mclag-0.3.1.dist-info/RECORD
